owo_pjt/__init__.py
owo_pjt-0.0.1.dist-info/METADATA
owo_pjt-0.0.1.dist-info/WHEEL
owo_pjt-0.0.1.dist-info/top_level.txt
owo_pjt-0.0.1.dist-info/RECORD
